{
  "parent": "minecraft:recipes/root",
  "criteria": {
    "has_quarter_piece": {
      "conditions": {
        "items": [
          {
            "items": [
              "extshape_blockus:oak_small_logs_quarter_piece"
            ]
          }
        ]
      },
      "trigger": "minecraft:inventory_changed"
    },
    "has_the_recipe": {
      "conditions": {
        "recipe": "extshape_blockus:oak_small_logs_vertical_quarter_piece"
      },
      "trigger": "minecraft:recipe_unlocked"
    }
  },
  "requirements": [
    [
      "has_the_recipe",
      "has_quarter_piece"
    ]
  ],
  "rewards": {
    "recipes": [
      "extshape_blockus:oak_small_logs_vertical_quarter_piece"
    ]
  },
  "sends_telemetry_event": false
}